db_utils/__init__.py
db_utils/build_query.py
db_utils/db_config.py
db_utils/db_manager.py
db_utils/exception.py
db_utils/interfaces/__init__.py
db_utils/interfaces/base_interface.py
db_utils/interfaces/databricks_interface.py
db_utils/interfaces/db2_interface.py
db_utils/interfaces/mysql_interface.py
db_utils/interfaces/oracle_interface.py
db_utils/interfaces/postgresql_interface.py
db_utils/interfaces/redshift_interface.py
db_utils/interfaces/snowflake_interface.py
db_utils/interfaces/sqlalchemy_interface.py
db_utils/interfaces/sqlite_interface.py
db_utils/interfaces/sqlserver_interface.py
db_utils/interfaces/teradata_interface.py
db_utils/utils.py
pyspdbutils-1.0.8.dist-info/LICENSE
pyspdbutils-1.0.8.dist-info/METADATA
pyspdbutils-1.0.8.dist-info/WHEEL
pyspdbutils-1.0.8.dist-info/RECORD
