Metadata-Version: 2.3
Name: pyspdbutils
Version: 1.0.8
Summary: Production-grade database utilities with universal interface and hash collision detection
License: MIT
Keywords: database,sql,orm,utilities,postgresql,mysql,sqlite,oracle,snowflake,databricks,redshift,teradata
Author: Debi Prasad Rath
Author-email: debi.rath817@gmail.com
Maintainer: Sanjeev Kumar Pandey
Maintainer-email: sanjeev9088@gmail.com
Requires-Python: >=3.8,<4.0
Classifier: Development Status :: 5 - Production/Stable
Classifier: Intended Audience :: Developers
Classifier: License :: OSI Approved :: MIT License
Classifier: Operating System :: OS Independent
Classifier: Programming Language :: Python :: 3
Classifier: Programming Language :: Python :: 3.8
Classifier: Programming Language :: Python :: 3.9
Classifier: Programming Language :: Python :: 3.10
Classifier: Programming Language :: Python :: 3.11
Classifier: Programming Language :: Python :: 3.12
Classifier: Programming Language :: Python :: 3.13
Classifier: Topic :: Database
Classifier: Topic :: Software Development :: Libraries :: Python Modules
Classifier: Topic :: Utilities
Provides-Extra: all
Provides-Extra: databricks
Provides-Extra: db2
Provides-Extra: mysql
Provides-Extra: oracle
Provides-Extra: postgresql
Provides-Extra: redshift
Provides-Extra: snowflake
Provides-Extra: sqlserver
Provides-Extra: teradata
Requires-Dist: PyMySQL (>=1.1.0,<2.0.0) ; extra == "mysql" or extra == "all"
Requires-Dist: databricks-sql-connector (>=3.2.0,<4.0.0) ; extra == "databricks" or extra == "all"
Requires-Dist: ibm-db (>=3.2.0,<4.0.0) ; extra == "db2" or extra == "all"
Requires-Dist: mysql-connector-python (>=8.4.0,<9.0.0) ; extra == "mysql" or extra == "all"
Requires-Dist: oracledb (>=2.2.0,<3.0.0) ; extra == "oracle" or extra == "all"
Requires-Dist: psycopg2-binary (>=2.9.9,<3.0.0) ; extra == "postgresql" or extra == "all"
Requires-Dist: pyodbc (>=5.1.0,<6.0.0) ; extra == "sqlserver" or extra == "all"
Requires-Dist: python-dotenv (>=1.0.0,<2.0.0)
Requires-Dist: redshift-connector (>=2.1.0,<3.0.0) ; extra == "redshift" or extra == "all"
Requires-Dist: snowflake-connector-python (>=3.11.0,<4.0.0) ; extra == "snowflake" or extra == "all"
Requires-Dist: sqlalchemy (>=2.0.0,<3.0.0)
Requires-Dist: teradatasql (>=20.0.0,<21.0.0) ; extra == "teradata" or extra == "all"
Project-URL: Documentation, https://github.com/yourusername/pyspdbutils#readme
Project-URL: Homepage, https://github.com/yourusername/pyspdbutils
Project-URL: Repository, https://github.com/yourusername/pyspdbutils
